{
    "traceID": "1006eceb986dbd05",
    "spans": [
        {
            "traceID": "1006eceb986dbd05",
            "spanID": "53597b48010d012c",
            "flags": 1,
            "operationName": "UploadText",
            "references": [
                {
                    "refType": "CHILD_OF",
                    "traceID": "1006eceb986dbd05",
                    "spanID": "02ea154271495de5"
                }
            ],
            "startTime": 1682628697993430,
            "duration": 935,
            "tags": [
                {
                    "key": "internal.span.format",
                    "type": "string",
                    "value": "proto"
                }
            ],
            "logs": [],
            "processID": "p1",
            "warnings": null
        },
        {
            "traceID": "1006eceb986dbd05",
            "spanID": "34736727c7a65084",
            "flags": 1,
            "operationName": "MongoUpdate.",
            "references": [
                {
                    "refType": "CHILD_OF",
                    "traceID": "1006eceb986dbd05",
                    "spanID": "6a35bd7c66f0eb7d"
                }
            ],
            "startTime": 1682628697995511,
            "duration": 485,
            "tags": [
                {
                    "key": "internal.span.format",
                    "type": "string",
                    "value": "proto"
                }
            ],
            "logs": [],
            "processID": "p2",
            "warnings": null
        },
        {
            "traceID": "1006eceb986dbd05",
            "spanID": "990cda074ef29813",
            "flags": 1,
            "operationName": "RedisUpdate",
            "references": [
                {
                    "refType": "CHILD_OF",
                    "traceID": "1006eceb986dbd05",
                    "spanID": "6a35bd7c66f0eb7d"
                }
            ],
            "startTime": 1682628697996025,
            "duration": 389,
            "tags": [
                {
                    "key": "internal.span.format",
                    "type": "string",
                    "value": "proto"
                }
            ],
            "logs": [],
            "processID": "p2",
            "warnings": null
        },
        {
            "traceID": "1006eceb986dbd05",
            "spanID": "6a35bd7c66f0eb7d",
            "flags": 1,
            "operationName": "UploadMovieReview",
            "references": [
                {
                    "refType": "CHILD_OF",
                    "traceID": "1006eceb986dbd05",
                    "spanID": "6e99247ced773584"
                }
            ],
            "startTime": 1682628697995123,
            "duration": 1303,
            "tags": [
                {
                    "key": "internal.span.format",
                    "type": "string",
                    "value": "proto"
                }
            ],
            "logs": [],
            "processID": "p2",
            "warnings": null
        },
        {
            "traceID": "1006eceb986dbd05",
            "spanID": "7d2ce116dd0e01ec",
            "flags": 1,
            "operationName": "MongoFindMovie",
            "references": [
                {
                    "refType": "CHILD_OF",
                    "traceID": "1006eceb986dbd05",
                    "spanID": "6a35bd7c66f0eb7d"
                }
            ],
            "startTime": 1682628697995141,
            "duration": 1288,
            "tags": [
                {
                    "key": "internal.span.format",
                    "type": "string",
                    "value": "proto"
                }
            ],
            "logs": [],
            "processID": "p2",
            "warnings": null
        },
        {
            "traceID": "1006eceb986dbd05",
            "spanID": "753f4ce14e97d536",
            "flags": 1,
            "operationName": "MmcGetMovieId",
            "references": [
                {
                    "refType": "CHILD_OF",
                    "traceID": "1006eceb986dbd05",
                    "spanID": "1b8d694f181af1ad"
                }
            ],
            "startTime": 1682628697993219,
            "duration": 203,
            "tags": [
                {
                    "key": "internal.span.format",
                    "type": "string",
                    "value": "proto"
                }
            ],
            "logs": [],
            "processID": "p3",
            "warnings": null
        },
        {
            "traceID": "1006eceb986dbd05",
            "spanID": "287fd56168a45c9d",
            "flags": 1,
            "operationName": "MmcSetMovieId",
            "references": [
                {
                    "refType": "CHILD_OF",
                    "traceID": "1006eceb986dbd05",
                    "spanID": "1b8d694f181af1ad"
                }
            ],
            "startTime": 1682628697993654,
            "duration": 103,
            "tags": [
                {
                    "key": "internal.span.format",
                    "type": "string",
                    "value": "proto"
                }
            ],
            "logs": [],
            "processID": "p3",
            "warnings": null
        },
        {
            "traceID": "1006eceb986dbd05",
            "spanID": "1b8d694f181af1ad",
            "flags": 1,
            "operationName": "UploadMovieId",
            "references": [
                {
                    "refType": "CHILD_OF",
                    "traceID": "1006eceb986dbd05",
                    "spanID": "02ea154271495de5"
                }
            ],
            "startTime": 1682628697993207,
            "duration": 3560,
            "tags": [
                {
                    "key": "internal.span.format",
                    "type": "string",
                    "value": "proto"
                }
            ],
            "logs": [],
            "processID": "p3",
            "warnings": null
        },
        {
            "traceID": "1006eceb986dbd05",
            "spanID": "02ea154271495de5",
            "flags": 1,
            "operationName": "ComposeReview",
            "references": [
                {
                    "refType": "CHILD_OF",
                    "traceID": "1006eceb986dbd05",
                    "spanID": "252ca121466792b6"
                }
            ],
            "startTime": 1682628697992759,
            "duration": 4358,
            "tags": [
                {
                    "key": "internal.span.format",
                    "type": "string",
                    "value": "proto"
                }
            ],
            "logs": [],
            "processID": "p4",
            "warnings": null
        },
        {
            "traceID": "1006eceb986dbd05",
            "spanID": "252ca121466792b6",
            "flags": 1,
            "operationName": "/wrk2-api/review/compose",
            "references": [
                {
                    "refType": "CHILD_OF",
                    "traceID": "1006eceb986dbd05",
                    "spanID": "1006eceb986dbd05"
                }
            ],
            "startTime": 1682628697992717,
            "duration": 4448,
            "tags": [
                {
                    "key": "component",
                    "type": "string",
                    "value": "nginx"
                },
                {
                    "key": "nginx.worker_pid",
                    "type": "string",
                    "value": "11"
                },
                {
                    "key": "peer.address",
                    "type": "string",
                    "value": "172.18.0.1:40622"
                },
                {
                    "key": "http.method",
                    "type": "string",
                    "value": "POST"
                },
                {
                    "key": "http.url",
                    "type": "string",
                    "value": "http://localhost:8080/wrk2-api/review/compose/wrk2-api/review/compose"
                },
                {
                    "key": "http.host",
                    "type": "string",
                    "value": "localhost:8080"
                },
                {
                    "key": "http.status_code",
                    "type": "int64",
                    "value": 200
                },
                {
                    "key": "http.status_line",
                    "type": "string",
                    "value": ""
                },
                {
                    "key": "internal.span.format",
                    "type": "string",
                    "value": "proto"
                }
            ],
            "logs": [],
            "processID": "p4",
            "warnings": null
        },
        {
            "traceID": "1006eceb986dbd05",
            "spanID": "1006eceb986dbd05",
            "flags": 1,
            "operationName": "/wrk2-api/review/compose",
            "references": [],
            "startTime": 1682628697992000,
            "duration": 5165,
            "tags": [
                {
                    "key": "sampler.type",
                    "type": "string",
                    "value": "const"
                },
                {
                    "key": "sampler.param",
                    "type": "bool",
                    "value": true
                },
                {
                    "key": "http.status_code",
                    "type": "int64",
                    "value": 200
                },
                {
                    "key": "http.status_line",
                    "type": "string",
                    "value": ""
                },
                {
                    "key": "component",
                    "type": "string",
                    "value": "nginx"
                },
                {
                    "key": "nginx.worker_pid",
                    "type": "string",
                    "value": "11"
                },
                {
                    "key": "peer.address",
                    "type": "string",
                    "value": "172.18.0.1:40622"
                },
                {
                    "key": "http.method",
                    "type": "string",
                    "value": "POST"
                },
                {
                    "key": "http.url",
                    "type": "string",
                    "value": "http://localhost:8080/wrk2-api/review/compose/wrk2-api/review/compose"
                },
                {
                    "key": "http.host",
                    "type": "string",
                    "value": "localhost:8080"
                },
                {
                    "key": "internal.span.format",
                    "type": "string",
                    "value": "proto"
                }
            ],
            "logs": [],
            "processID": "p4",
            "warnings": null
        },
        {
            "traceID": "1006eceb986dbd05",
            "spanID": "5041ffe64508ef63",
            "flags": 1,
            "operationName": "MongoInsertReview",
            "references": [
                {
                    "refType": "CHILD_OF",
                    "traceID": "1006eceb986dbd05",
                    "spanID": "1b6ae3e437ee9fdd"
                }
            ],
            "startTime": 1682628697995239,
            "duration": 341,
            "tags": [
                {
                    "key": "internal.span.format",
                    "type": "string",
                    "value": "proto"
                }
            ],
            "logs": [],
            "processID": "p5",
            "warnings": null
        },
        {
            "traceID": "1006eceb986dbd05",
            "spanID": "1b6ae3e437ee9fdd",
            "flags": 1,
            "operationName": "StoreReview",
            "references": [
                {
                    "refType": "CHILD_OF",
                    "traceID": "1006eceb986dbd05",
                    "spanID": "6e99247ced773584"
                }
            ],
            "startTime": 1682628697995211,
            "duration": 385,
            "tags": [
                {
                    "key": "internal.span.format",
                    "type": "string",
                    "value": "proto"
                }
            ],
            "logs": [],
            "processID": "p5",
            "warnings": null
        },
        {
            "traceID": "1006eceb986dbd05",
            "spanID": "0a83fbbf1f148117",
            "flags": 1,
            "operationName": "UploadUserId",
            "references": [
                {
                    "refType": "CHILD_OF",
                    "traceID": "1006eceb986dbd05",
                    "spanID": "ee00ab390fa054a2"
                }
            ],
            "startTime": 1682628697993292,
            "duration": 511,
            "tags": [
                {
                    "key": "internal.span.format",
                    "type": "string",
                    "value": "proto"
                }
            ],
            "logs": [],
            "processID": "p6",
            "warnings": null
        },
        {
            "traceID": "1006eceb986dbd05",
            "spanID": "4377ce83980edd67",
            "flags": 1,
            "operationName": "UploadText",
            "references": [
                {
                    "refType": "CHILD_OF",
                    "traceID": "1006eceb986dbd05",
                    "spanID": "53597b48010d012c"
                }
            ],
            "startTime": 1682628697993536,
            "duration": 676,
            "tags": [
                {
                    "key": "internal.span.format",
                    "type": "string",
                    "value": "proto"
                }
            ],
            "logs": [],
            "processID": "p6",
            "warnings": null
        },
        {
            "traceID": "1006eceb986dbd05",
            "spanID": "3353e2cc13989cff",
            "flags": 1,
            "operationName": "UploadMovieId",
            "references": [
                {
                    "refType": "CHILD_OF",
                    "traceID": "1006eceb986dbd05",
                    "spanID": "1b8d694f181af1ad"
                }
            ],
            "startTime": 1682628697993748,
            "duration": 670,
            "tags": [
                {
                    "key": "internal.span.format",
                    "type": "string",
                    "value": "proto"
                }
            ],
            "logs": [],
            "processID": "p6",
            "warnings": null
        },
        {
            "traceID": "1006eceb986dbd05",
            "spanID": "de5e430f8f858810",
            "flags": 1,
            "operationName": "UploadUniqueId",
            "references": [
                {
                    "refType": "CHILD_OF",
                    "traceID": "1006eceb986dbd05",
                    "spanID": "3dc317bbcf6c096b"
                }
            ],
            "startTime": 1682628697993780,
            "duration": 693,
            "tags": [
                {
                    "key": "internal.span.format",
                    "type": "string",
                    "value": "proto"
                }
            ],
            "logs": [],
            "processID": "p6",
            "warnings": null
        },
        {
            "traceID": "1006eceb986dbd05",
            "spanID": "6e99247ced773584",
            "flags": 1,
            "operationName": "UploadRating",
            "references": [
                {
                    "refType": "CHILD_OF",
                    "traceID": "1006eceb986dbd05",
                    "spanID": "bbb4e0d4fbe3b041"
                }
            ],
            "startTime": 1682628697994028,
            "duration": 2506,
            "tags": [
                {
                    "key": "internal.span.format",
                    "type": "string",
                    "value": "proto"
                }
            ],
            "logs": [],
            "processID": "p6",
            "warnings": null
        },
        {
            "traceID": "1006eceb986dbd05",
            "spanID": "6d3436e51af74c7d",
            "flags": 1,
            "operationName": "MongoUpdate",
            "references": [
                {
                    "refType": "CHILD_OF",
                    "traceID": "1006eceb986dbd05",
                    "spanID": "710193717a99f901"
                }
            ],
            "startTime": 1682628697995478,
            "duration": 462,
            "tags": [
                {
                    "key": "internal.span.format",
                    "type": "string",
                    "value": "proto"
                }
            ],
            "logs": [],
            "processID": "p7",
            "warnings": null
        },
        {
            "traceID": "1006eceb986dbd05",
            "spanID": "57b608d26bbe3b7e",
            "flags": 1,
            "operationName": "RedisUpdate",
            "references": [
                {
                    "refType": "CHILD_OF",
                    "traceID": "1006eceb986dbd05",
                    "spanID": "710193717a99f901"
                }
            ],
            "startTime": 1682628697995967,
            "duration": 246,
            "tags": [
                {
                    "key": "internal.span.format",
                    "type": "string",
                    "value": "proto"
                }
            ],
            "logs": [],
            "processID": "p7",
            "warnings": null
        },
        {
            "traceID": "1006eceb986dbd05",
            "spanID": "710193717a99f901",
            "flags": 1,
            "operationName": "UploadUserReview",
            "references": [
                {
                    "refType": "CHILD_OF",
                    "traceID": "1006eceb986dbd05",
                    "spanID": "6e99247ced773584"
                }
            ],
            "startTime": 1682628697995092,
            "duration": 1128,
            "tags": [
                {
                    "key": "internal.span.format",
                    "type": "string",
                    "value": "proto"
                }
            ],
            "logs": [],
            "processID": "p7",
            "warnings": null
        },
        {
            "traceID": "1006eceb986dbd05",
            "spanID": "8af58ad62b389699",
            "flags": 1,
            "operationName": "MongoFindUser",
            "references": [
                {
                    "refType": "CHILD_OF",
                    "traceID": "1006eceb986dbd05",
                    "spanID": "710193717a99f901"
                }
            ],
            "startTime": 1682628697995120,
            "duration": 1103,
            "tags": [
                {
                    "key": "internal.span.format",
                    "type": "string",
                    "value": "proto"
                }
            ],
            "logs": [],
            "processID": "p7",
            "warnings": null
        },
        {
            "traceID": "1006eceb986dbd05",
            "spanID": "3dc317bbcf6c096b",
            "flags": 1,
            "operationName": "UploadUniqueId",
            "references": [
                {
                    "refType": "CHILD_OF",
                    "traceID": "1006eceb986dbd05",
                    "spanID": "02ea154271495de5"
                }
            ],
            "startTime": 1682628697993596,
            "duration": 941,
            "tags": [
                {
                    "key": "internal.span.format",
                    "type": "string",
                    "value": "proto"
                }
            ],
            "logs": [],
            "processID": "p8",
            "warnings": null
        },
        {
            "traceID": "1006eceb986dbd05",
            "spanID": "ee00ab390fa054a2",
            "flags": 1,
            "operationName": "UploadUserWithUsername",
            "references": [
                {
                    "refType": "CHILD_OF",
                    "traceID": "1006eceb986dbd05",
                    "spanID": "02ea154271495de5"
                }
            ],
            "startTime": 1682628697992951,
            "duration": 913,
            "tags": [
                {
                    "key": "internal.span.format",
                    "type": "string",
                    "value": "proto"
                }
            ],
            "logs": [],
            "processID": "p9",
            "warnings": null
        },
        {
            "traceID": "1006eceb986dbd05",
            "spanID": "c2b8b4deaf70cea6",
            "flags": 1,
            "operationName": "MmcGetUserId",
            "references": [
                {
                    "refType": "CHILD_OF",
                    "traceID": "1006eceb986dbd05",
                    "spanID": "ee00ab390fa054a2"
                }
            ],
            "startTime": 1682628697992969,
            "duration": 121,
            "tags": [
                {
                    "key": "internal.span.format",
                    "type": "string",
                    "value": "proto"
                }
            ],
            "logs": [],
            "processID": "p9",
            "warnings": null
        },
        {
            "traceID": "1006eceb986dbd05",
            "spanID": "0caa0e00e579fa2b",
            "flags": 1,
            "operationName": "RedisInsert",
            "references": [
                {
                    "refType": "CHILD_OF",
                    "traceID": "1006eceb986dbd05",
                    "spanID": "bbb4e0d4fbe3b041"
                }
            ],
            "startTime": 1682628697994042,
            "duration": 345,
            "tags": [
                {
                    "key": "internal.span.format",
                    "type": "string",
                    "value": "proto"
                }
            ],
            "logs": [],
            "processID": "p10",
            "warnings": null
        },
        {
            "traceID": "1006eceb986dbd05",
            "spanID": "bbb4e0d4fbe3b041",
            "flags": 1,
            "operationName": "UploadRating",
            "references": [
                {
                    "refType": "CHILD_OF",
                    "traceID": "1006eceb986dbd05",
                    "spanID": "1b8d694f181af1ad"
                }
            ],
            "startTime": 1682628697993824,
            "duration": 2814,
            "tags": [
                {
                    "key": "internal.span.format",
                    "type": "string",
                    "value": "proto"
                }
            ],
            "logs": [],
            "processID": "p10",
            "warnings": null
        }
    ],
    "processes": {
        "p1": {
            "serviceName": "text-service",
            "tags": [
                {
                    "key": "hostname",
                    "type": "string",
                    "value": "text-service"
                },
                {
                    "key": "ip",
                    "type": "string",
                    "value": "127.0.0.1"
                },
                {
                    "key": "jaeger.version",
                    "type": "string",
                    "value": "C++-0.4.2"
                }
            ]
        },
        "p10": {
            "serviceName": "rating-service",
            "tags": [
                {
                    "key": "hostname",
                    "type": "string",
                    "value": "rating-service"
                },
                {
                    "key": "ip",
                    "type": "string",
                    "value": "127.0.0.1"
                },
                {
                    "key": "jaeger.version",
                    "type": "string",
                    "value": "C++-0.4.2"
                }
            ]
        },
        "p2": {
            "serviceName": "movie-review-service",
            "tags": [
                {
                    "key": "hostname",
                    "type": "string",
                    "value": "movie-review-service"
                },
                {
                    "key": "ip",
                    "type": "string",
                    "value": "127.0.0.1"
                },
                {
                    "key": "jaeger.version",
                    "type": "string",
                    "value": "C++-0.4.2"
                }
            ]
        },
        "p3": {
            "serviceName": "movie-id-service",
            "tags": [
                {
                    "key": "hostname",
                    "type": "string",
                    "value": "movie-id-service"
                },
                {
                    "key": "ip",
                    "type": "string",
                    "value": "127.0.0.1"
                },
                {
                    "key": "jaeger.version",
                    "type": "string",
                    "value": "C++-0.4.2"
                }
            ]
        },
        "p4": {
            "serviceName": "nginx",
            "tags": [
                {
                    "key": "hostname",
                    "type": "string",
                    "value": "nginx-thrift"
                },
                {
                    "key": "ip",
                    "type": "string",
                    "value": "127.0.0.1"
                },
                {
                    "key": "jaeger.version",
                    "type": "string",
                    "value": "C++-0.4.2"
                }
            ]
        },
        "p5": {
            "serviceName": "review-storage-service",
            "tags": [
                {
                    "key": "hostname",
                    "type": "string",
                    "value": "review-storage-service"
                },
                {
                    "key": "ip",
                    "type": "string",
                    "value": "127.0.0.1"
                },
                {
                    "key": "jaeger.version",
                    "type": "string",
                    "value": "C++-0.4.2"
                }
            ]
        },
        "p6": {
            "serviceName": "compose-review-service",
            "tags": [
                {
                    "key": "hostname",
                    "type": "string",
                    "value": "compose-review-service"
                },
                {
                    "key": "ip",
                    "type": "string",
                    "value": "127.0.0.1"
                },
                {
                    "key": "jaeger.version",
                    "type": "string",
                    "value": "C++-0.4.2"
                }
            ]
        },
        "p7": {
            "serviceName": "user-review-service",
            "tags": [
                {
                    "key": "hostname",
                    "type": "string",
                    "value": "user-review-service"
                },
                {
                    "key": "ip",
                    "type": "string",
                    "value": "127.0.0.1"
                },
                {
                    "key": "jaeger.version",
                    "type": "string",
                    "value": "C++-0.4.2"
                }
            ]
        },
        "p8": {
            "serviceName": "unique-id-service",
            "tags": [
                {
                    "key": "hostname",
                    "type": "string",
                    "value": "unique-id-service"
                },
                {
                    "key": "ip",
                    "type": "string",
                    "value": "127.0.0.1"
                },
                {
                    "key": "jaeger.version",
                    "type": "string",
                    "value": "C++-0.4.2"
                }
            ]
        },
        "p9": {
            "serviceName": "user-service",
            "tags": [
                {
                    "key": "hostname",
                    "type": "string",
                    "value": "user-service"
                },
                {
                    "key": "ip",
                    "type": "string",
                    "value": "127.0.0.1"
                },
                {
                    "key": "jaeger.version",
                    "type": "string",
                    "value": "C++-0.4.2"
                }
            ]
        }
    },
    "warnings": null
}