{
    "traceID": "94acd369009a1f95",
    "spans": [
        {
            "traceID": "94acd369009a1f95",
            "spanID": "028520088d256706",
            "flags": 1,
            "operationName": "MmcGetUserId",
            "references": [
                {
                    "refType": "CHILD_OF",
                    "traceID": "94acd369009a1f95",
                    "spanID": "a8be194d2008a8d8"
                }
            ],
            "startTime": 1682628697957680,
            "duration": 104,
            "tags": [
                {
                    "key": "internal.span.format",
                    "type": "string",
                    "value": "proto"
                }
            ],
            "logs": [],
            "processID": "p1",
            "warnings": null
        },
        {
            "traceID": "94acd369009a1f95",
            "spanID": "a8be194d2008a8d8",
            "flags": 1,
            "operationName": "UploadUserWithUsername",
            "references": [
                {
                    "refType": "CHILD_OF",
                    "traceID": "94acd369009a1f95",
                    "spanID": "1fa5482b35dc590d"
                }
            ],
            "startTime": 1682628697957662,
            "duration": 940,
            "tags": [
                {
                    "key": "internal.span.format",
                    "type": "string",
                    "value": "proto"
                }
            ],
            "logs": [],
            "processID": "p1",
            "warnings": null
        },
        {
            "traceID": "94acd369009a1f95",
            "spanID": "82da040e655dd717",
            "flags": 1,
            "operationName": "RedisUpdate",
            "references": [
                {
                    "refType": "CHILD_OF",
                    "traceID": "94acd369009a1f95",
                    "spanID": "acb2bb6f4d3279db"
                }
            ],
            "startTime": 1682628697960730,
            "duration": 314,
            "tags": [
                {
                    "key": "internal.span.format",
                    "type": "string",
                    "value": "proto"
                }
            ],
            "logs": [],
            "processID": "p2",
            "warnings": null
        },
        {
            "traceID": "94acd369009a1f95",
            "spanID": "8c35615e9ac1b8b1",
            "flags": 1,
            "operationName": "MongoFindUser",
            "references": [
                {
                    "refType": "CHILD_OF",
                    "traceID": "94acd369009a1f95",
                    "spanID": "acb2bb6f4d3279db"
                }
            ],
            "startTime": 1682628697959795,
            "duration": 1259,
            "tags": [
                {
                    "key": "internal.span.format",
                    "type": "string",
                    "value": "proto"
                }
            ],
            "logs": [],
            "processID": "p2",
            "warnings": null
        },
        {
            "traceID": "94acd369009a1f95",
            "spanID": "9b92d44a3dfd20e8",
            "flags": 1,
            "operationName": "MongoUpdate",
            "references": [
                {
                    "refType": "CHILD_OF",
                    "traceID": "94acd369009a1f95",
                    "spanID": "acb2bb6f4d3279db"
                }
            ],
            "startTime": 1682628697960189,
            "duration": 513,
            "tags": [
                {
                    "key": "internal.span.format",
                    "type": "string",
                    "value": "proto"
                }
            ],
            "logs": [],
            "processID": "p2",
            "warnings": null
        },
        {
            "traceID": "94acd369009a1f95",
            "spanID": "acb2bb6f4d3279db",
            "flags": 1,
            "operationName": "UploadUserReview",
            "references": [
                {
                    "refType": "CHILD_OF",
                    "traceID": "94acd369009a1f95",
                    "spanID": "c829cfe9dbbf09bd"
                }
            ],
            "startTime": 1682628697959776,
            "duration": 1275,
            "tags": [
                {
                    "key": "internal.span.format",
                    "type": "string",
                    "value": "proto"
                }
            ],
            "logs": [],
            "processID": "p2",
            "warnings": null
        },
        {
            "traceID": "94acd369009a1f95",
            "spanID": "c59df3eb5dea9b1f",
            "flags": 1,
            "operationName": "UploadText",
            "references": [
                {
                    "refType": "CHILD_OF",
                    "traceID": "94acd369009a1f95",
                    "spanID": "3165c34050748967"
                }
            ],
            "startTime": 1682628697957974,
            "duration": 356,
            "tags": [
                {
                    "key": "internal.span.format",
                    "type": "string",
                    "value": "proto"
                }
            ],
            "logs": [],
            "processID": "p3",
            "warnings": null
        },
        {
            "traceID": "94acd369009a1f95",
            "spanID": "811d5e406c462297",
            "flags": 1,
            "operationName": "UploadUserId",
            "references": [
                {
                    "refType": "CHILD_OF",
                    "traceID": "94acd369009a1f95",
                    "spanID": "a8be194d2008a8d8"
                }
            ],
            "startTime": 1682628697957979,
            "duration": 542,
            "tags": [
                {
                    "key": "internal.span.format",
                    "type": "string",
                    "value": "proto"
                }
            ],
            "logs": [],
            "processID": "p3",
            "warnings": null
        },
        {
            "traceID": "94acd369009a1f95",
            "spanID": "2a5608cdc2f457f3",
            "flags": 1,
            "operationName": "UploadUniqueId",
            "references": [
                {
                    "refType": "CHILD_OF",
                    "traceID": "94acd369009a1f95",
                    "spanID": "9a305d170f13fc0b"
                }
            ],
            "startTime": 1682628697958108,
            "duration": 436,
            "tags": [
                {
                    "key": "internal.span.format",
                    "type": "string",
                    "value": "proto"
                }
            ],
            "logs": [],
            "processID": "p3",
            "warnings": null
        },
        {
            "traceID": "94acd369009a1f95",
            "spanID": "55937c9c91b5a021",
            "flags": 1,
            "operationName": "UploadMovieId",
            "references": [
                {
                    "refType": "CHILD_OF",
                    "traceID": "94acd369009a1f95",
                    "spanID": "f639e01c683069e9"
                }
            ],
            "startTime": 1682628697958396,
            "duration": 448,
            "tags": [
                {
                    "key": "internal.span.format",
                    "type": "string",
                    "value": "proto"
                }
            ],
            "logs": [],
            "processID": "p3",
            "warnings": null
        },
        {
            "traceID": "94acd369009a1f95",
            "spanID": "c829cfe9dbbf09bd",
            "flags": 1,
            "operationName": "UploadRating",
            "references": [
                {
                    "refType": "CHILD_OF",
                    "traceID": "94acd369009a1f95",
                    "spanID": "c9446563a3955ce7"
                }
            ],
            "startTime": 1682628697958792,
            "duration": 2384,
            "tags": [
                {
                    "key": "internal.span.format",
                    "type": "string",
                    "value": "proto"
                }
            ],
            "logs": [],
            "processID": "p3",
            "warnings": null
        },
        {
            "traceID": "94acd369009a1f95",
            "spanID": "8f1ee8878838afc1",
            "flags": 1,
            "operationName": "RedisInsert",
            "references": [
                {
                    "refType": "CHILD_OF",
                    "traceID": "94acd369009a1f95",
                    "spanID": "c9446563a3955ce7"
                }
            ],
            "startTime": 1682628697958698,
            "duration": 233,
            "tags": [
                {
                    "key": "internal.span.format",
                    "type": "string",
                    "value": "proto"
                }
            ],
            "logs": [],
            "processID": "p4",
            "warnings": null
        },
        {
            "traceID": "94acd369009a1f95",
            "spanID": "c9446563a3955ce7",
            "flags": 1,
            "operationName": "UploadRating",
            "references": [
                {
                    "refType": "CHILD_OF",
                    "traceID": "94acd369009a1f95",
                    "spanID": "f639e01c683069e9"
                }
            ],
            "startTime": 1682628697958560,
            "duration": 2773,
            "tags": [
                {
                    "key": "internal.span.format",
                    "type": "string",
                    "value": "proto"
                }
            ],
            "logs": [],
            "processID": "p4",
            "warnings": null
        },
        {
            "traceID": "94acd369009a1f95",
            "spanID": "3165c34050748967",
            "flags": 1,
            "operationName": "UploadText",
            "references": [
                {
                    "refType": "CHILD_OF",
                    "traceID": "94acd369009a1f95",
                    "spanID": "1fa5482b35dc590d"
                }
            ],
            "startTime": 1682628697957855,
            "duration": 544,
            "tags": [
                {
                    "key": "internal.span.format",
                    "type": "string",
                    "value": "proto"
                }
            ],
            "logs": [],
            "processID": "p5",
            "warnings": null
        },
        {
            "traceID": "94acd369009a1f95",
            "spanID": "6fc0ff846ee749a5",
            "flags": 1,
            "operationName": "/wrk2-api/review/compose",
            "references": [
                {
                    "refType": "CHILD_OF",
                    "traceID": "94acd369009a1f95",
                    "spanID": "94acd369009a1f95"
                }
            ],
            "startTime": 1682628697957465,
            "duration": 4223,
            "tags": [
                {
                    "key": "component",
                    "type": "string",
                    "value": "nginx"
                },
                {
                    "key": "nginx.worker_pid",
                    "type": "string",
                    "value": "8"
                },
                {
                    "key": "peer.address",
                    "type": "string",
                    "value": "172.18.0.1:40646"
                },
                {
                    "key": "http.method",
                    "type": "string",
                    "value": "POST"
                },
                {
                    "key": "http.url",
                    "type": "string",
                    "value": "http://localhost:8080/wrk2-api/review/compose/wrk2-api/review/compose"
                },
                {
                    "key": "http.host",
                    "type": "string",
                    "value": "localhost:8080"
                },
                {
                    "key": "http.status_code",
                    "type": "int64",
                    "value": 200
                },
                {
                    "key": "http.status_line",
                    "type": "string",
                    "value": ""
                },
                {
                    "key": "internal.span.format",
                    "type": "string",
                    "value": "proto"
                }
            ],
            "logs": [],
            "processID": "p6",
            "warnings": null
        },
        {
            "traceID": "94acd369009a1f95",
            "spanID": "94acd369009a1f95",
            "flags": 1,
            "operationName": "/wrk2-api/review/compose",
            "references": [],
            "startTime": 1682628697957000,
            "duration": 4688,
            "tags": [
                {
                    "key": "sampler.type",
                    "type": "string",
                    "value": "const"
                },
                {
                    "key": "sampler.param",
                    "type": "bool",
                    "value": true
                },
                {
                    "key": "http.status_code",
                    "type": "int64",
                    "value": 200
                },
                {
                    "key": "http.status_line",
                    "type": "string",
                    "value": ""
                },
                {
                    "key": "component",
                    "type": "string",
                    "value": "nginx"
                },
                {
                    "key": "nginx.worker_pid",
                    "type": "string",
                    "value": "8"
                },
                {
                    "key": "peer.address",
                    "type": "string",
                    "value": "172.18.0.1:40646"
                },
                {
                    "key": "http.method",
                    "type": "string",
                    "value": "POST"
                },
                {
                    "key": "http.url",
                    "type": "string",
                    "value": "http://localhost:8080/wrk2-api/review/compose/wrk2-api/review/compose"
                },
                {
                    "key": "http.host",
                    "type": "string",
                    "value": "localhost:8080"
                },
                {
                    "key": "internal.span.format",
                    "type": "string",
                    "value": "proto"
                }
            ],
            "logs": [],
            "processID": "p6",
            "warnings": null
        },
        {
            "traceID": "94acd369009a1f95",
            "spanID": "1fa5482b35dc590d",
            "flags": 1,
            "operationName": "ComposeReview",
            "references": [
                {
                    "refType": "CHILD_OF",
                    "traceID": "94acd369009a1f95",
                    "spanID": "6fc0ff846ee749a5"
                }
            ],
            "startTime": 1682628697957505,
            "duration": 4142,
            "tags": [
                {
                    "key": "internal.span.format",
                    "type": "string",
                    "value": "proto"
                }
            ],
            "logs": [],
            "processID": "p6",
            "warnings": null
        },
        {
            "traceID": "94acd369009a1f95",
            "spanID": "4a7444fa26654204",
            "flags": 1,
            "operationName": "RedisUpdate",
            "references": [
                {
                    "refType": "CHILD_OF",
                    "traceID": "94acd369009a1f95",
                    "spanID": "22a87a6af2c9a86b"
                }
            ],
            "startTime": 1682628697960679,
            "duration": 313,
            "tags": [
                {
                    "key": "internal.span.format",
                    "type": "string",
                    "value": "proto"
                }
            ],
            "logs": [],
            "processID": "p7",
            "warnings": null
        },
        {
            "traceID": "94acd369009a1f95",
            "spanID": "7273a27b366a63a0",
            "flags": 1,
            "operationName": "MongoFindMovie",
            "references": [
                {
                    "refType": "CHILD_OF",
                    "traceID": "94acd369009a1f95",
                    "spanID": "22a87a6af2c9a86b"
                }
            ],
            "startTime": 1682628697959855,
            "duration": 1150,
            "tags": [
                {
                    "key": "internal.span.format",
                    "type": "string",
                    "value": "proto"
                }
            ],
            "logs": [],
            "processID": "p7",
            "warnings": null
        },
        {
            "traceID": "94acd369009a1f95",
            "spanID": "9f0c684168615f24",
            "flags": 1,
            "operationName": "MongoUpdate.",
            "references": [
                {
                    "refType": "CHILD_OF",
                    "traceID": "94acd369009a1f95",
                    "spanID": "22a87a6af2c9a86b"
                }
            ],
            "startTime": 1682628697960244,
            "duration": 407,
            "tags": [
                {
                    "key": "internal.span.format",
                    "type": "string",
                    "value": "proto"
                }
            ],
            "logs": [],
            "processID": "p7",
            "warnings": null
        },
        {
            "traceID": "94acd369009a1f95",
            "spanID": "22a87a6af2c9a86b",
            "flags": 1,
            "operationName": "UploadMovieReview",
            "references": [
                {
                    "refType": "CHILD_OF",
                    "traceID": "94acd369009a1f95",
                    "spanID": "c829cfe9dbbf09bd"
                }
            ],
            "startTime": 1682628697959831,
            "duration": 1169,
            "tags": [
                {
                    "key": "internal.span.format",
                    "type": "string",
                    "value": "proto"
                }
            ],
            "logs": [],
            "processID": "p7",
            "warnings": null
        },
        {
            "traceID": "94acd369009a1f95",
            "spanID": "fcf790a622a716b6",
            "flags": 1,
            "operationName": "MmcGetMovieId",
            "references": [
                {
                    "refType": "CHILD_OF",
                    "traceID": "94acd369009a1f95",
                    "spanID": "f639e01c683069e9"
                }
            ],
            "startTime": 1682628697957844,
            "duration": 97,
            "tags": [
                {
                    "key": "internal.span.format",
                    "type": "string",
                    "value": "proto"
                }
            ],
            "logs": [],
            "processID": "p8",
            "warnings": null
        },
        {
            "traceID": "94acd369009a1f95",
            "spanID": "867241b4fbf9fe14",
            "flags": 1,
            "operationName": "MmcSetMovieId",
            "references": [
                {
                    "refType": "CHILD_OF",
                    "traceID": "94acd369009a1f95",
                    "spanID": "f639e01c683069e9"
                }
            ],
            "startTime": 1682628697958312,
            "duration": 93,
            "tags": [
                {
                    "key": "internal.span.format",
                    "type": "string",
                    "value": "proto"
                }
            ],
            "logs": [],
            "processID": "p8",
            "warnings": null
        },
        {
            "traceID": "94acd369009a1f95",
            "spanID": "f639e01c683069e9",
            "flags": 1,
            "operationName": "UploadMovieId",
            "references": [
                {
                    "refType": "CHILD_OF",
                    "traceID": "94acd369009a1f95",
                    "spanID": "1fa5482b35dc590d"
                }
            ],
            "startTime": 1682628697957822,
            "duration": 3685,
            "tags": [
                {
                    "key": "internal.span.format",
                    "type": "string",
                    "value": "proto"
                }
            ],
            "logs": [],
            "processID": "p8",
            "warnings": null
        },
        {
            "traceID": "94acd369009a1f95",
            "spanID": "6c7d677fadc4de95",
            "flags": 1,
            "operationName": "MongoInsertReview",
            "references": [
                {
                    "refType": "CHILD_OF",
                    "traceID": "94acd369009a1f95",
                    "spanID": "86d5cf72d74ff9e6"
                }
            ],
            "startTime": 1682628697959765,
            "duration": 289,
            "tags": [
                {
                    "key": "internal.span.format",
                    "type": "string",
                    "value": "proto"
                }
            ],
            "logs": [],
            "processID": "p9",
            "warnings": null
        },
        {
            "traceID": "94acd369009a1f95",
            "spanID": "86d5cf72d74ff9e6",
            "flags": 1,
            "operationName": "StoreReview",
            "references": [
                {
                    "refType": "CHILD_OF",
                    "traceID": "94acd369009a1f95",
                    "spanID": "c829cfe9dbbf09bd"
                }
            ],
            "startTime": 1682628697959740,
            "duration": 335,
            "tags": [
                {
                    "key": "internal.span.format",
                    "type": "string",
                    "value": "proto"
                }
            ],
            "logs": [],
            "processID": "p9",
            "warnings": null
        },
        {
            "traceID": "94acd369009a1f95",
            "spanID": "9a305d170f13fc0b",
            "flags": 1,
            "operationName": "UploadUniqueId",
            "references": [
                {
                    "refType": "CHILD_OF",
                    "traceID": "94acd369009a1f95",
                    "spanID": "1fa5482b35dc590d"
                }
            ],
            "startTime": 1682628697957940,
            "duration": 665,
            "tags": [
                {
                    "key": "internal.span.format",
                    "type": "string",
                    "value": "proto"
                }
            ],
            "logs": [],
            "processID": "p10",
            "warnings": null
        }
    ],
    "processes": {
        "p1": {
            "serviceName": "user-service",
            "tags": [
                {
                    "key": "hostname",
                    "type": "string",
                    "value": "user-service"
                },
                {
                    "key": "ip",
                    "type": "string",
                    "value": "127.0.0.1"
                },
                {
                    "key": "jaeger.version",
                    "type": "string",
                    "value": "C++-0.4.2"
                }
            ]
        },
        "p10": {
            "serviceName": "unique-id-service",
            "tags": [
                {
                    "key": "hostname",
                    "type": "string",
                    "value": "unique-id-service"
                },
                {
                    "key": "ip",
                    "type": "string",
                    "value": "127.0.0.1"
                },
                {
                    "key": "jaeger.version",
                    "type": "string",
                    "value": "C++-0.4.2"
                }
            ]
        },
        "p2": {
            "serviceName": "user-review-service",
            "tags": [
                {
                    "key": "hostname",
                    "type": "string",
                    "value": "user-review-service"
                },
                {
                    "key": "ip",
                    "type": "string",
                    "value": "127.0.0.1"
                },
                {
                    "key": "jaeger.version",
                    "type": "string",
                    "value": "C++-0.4.2"
                }
            ]
        },
        "p3": {
            "serviceName": "compose-review-service",
            "tags": [
                {
                    "key": "hostname",
                    "type": "string",
                    "value": "compose-review-service"
                },
                {
                    "key": "ip",
                    "type": "string",
                    "value": "127.0.0.1"
                },
                {
                    "key": "jaeger.version",
                    "type": "string",
                    "value": "C++-0.4.2"
                }
            ]
        },
        "p4": {
            "serviceName": "rating-service",
            "tags": [
                {
                    "key": "hostname",
                    "type": "string",
                    "value": "rating-service"
                },
                {
                    "key": "ip",
                    "type": "string",
                    "value": "127.0.0.1"
                },
                {
                    "key": "jaeger.version",
                    "type": "string",
                    "value": "C++-0.4.2"
                }
            ]
        },
        "p5": {
            "serviceName": "text-service",
            "tags": [
                {
                    "key": "hostname",
                    "type": "string",
                    "value": "text-service"
                },
                {
                    "key": "ip",
                    "type": "string",
                    "value": "127.0.0.1"
                },
                {
                    "key": "jaeger.version",
                    "type": "string",
                    "value": "C++-0.4.2"
                }
            ]
        },
        "p6": {
            "serviceName": "nginx",
            "tags": [
                {
                    "key": "hostname",
                    "type": "string",
                    "value": "nginx-thrift"
                },
                {
                    "key": "ip",
                    "type": "string",
                    "value": "127.0.0.1"
                },
                {
                    "key": "jaeger.version",
                    "type": "string",
                    "value": "C++-0.4.2"
                }
            ]
        },
        "p7": {
            "serviceName": "movie-review-service",
            "tags": [
                {
                    "key": "hostname",
                    "type": "string",
                    "value": "movie-review-service"
                },
                {
                    "key": "ip",
                    "type": "string",
                    "value": "127.0.0.1"
                },
                {
                    "key": "jaeger.version",
                    "type": "string",
                    "value": "C++-0.4.2"
                }
            ]
        },
        "p8": {
            "serviceName": "movie-id-service",
            "tags": [
                {
                    "key": "hostname",
                    "type": "string",
                    "value": "movie-id-service"
                },
                {
                    "key": "ip",
                    "type": "string",
                    "value": "127.0.0.1"
                },
                {
                    "key": "jaeger.version",
                    "type": "string",
                    "value": "C++-0.4.2"
                }
            ]
        },
        "p9": {
            "serviceName": "review-storage-service",
            "tags": [
                {
                    "key": "hostname",
                    "type": "string",
                    "value": "review-storage-service"
                },
                {
                    "key": "ip",
                    "type": "string",
                    "value": "127.0.0.1"
                },
                {
                    "key": "jaeger.version",
                    "type": "string",
                    "value": "C++-0.4.2"
                }
            ]
        }
    },
    "warnings": null
}