{
    "traceID": "c1b550e8b0f4a312",
    "spans": [
        {
            "traceID": "c1b550e8b0f4a312",
            "spanID": "af3ff6f12b9ea5c0",
            "flags": 1,
            "operationName": "MongoInsertReview",
            "references": [
                {
                    "refType": "CHILD_OF",
                    "traceID": "c1b550e8b0f4a312",
                    "spanID": "3b4f6dcc57f14e48"
                }
            ],
            "startTime": 1682628698042602,
            "duration": 277,
            "tags": [
                {
                    "key": "internal.span.format",
                    "type": "string",
                    "value": "proto"
                }
            ],
            "logs": [],
            "processID": "p1",
            "warnings": null
        },
        {
            "traceID": "c1b550e8b0f4a312",
            "spanID": "b17b2ed2a11b4a73",
            "flags": 1,
            "operationName": "UploadUniqueId",
            "references": [
                {
                    "refType": "CHILD_OF",
                    "traceID": "c1b550e8b0f4a312",
                    "spanID": "06ac2c6ad3e8a69c"
                }
            ],
            "startTime": 1682628698041551,
            "duration": 341,
            "tags": [
                {
                    "key": "internal.span.format",
                    "type": "string",
                    "value": "proto"
                }
            ],
            "logs": [],
            "processID": "p2",
            "warnings": null
        },
        {
            "traceID": "c1b550e8b0f4a312",
            "spanID": "366b550b2fc971de",
            "flags": 1,
            "operationName": "UploadUserId",
            "references": [
                {
                    "refType": "CHILD_OF",
                    "traceID": "c1b550e8b0f4a312",
                    "spanID": "dff5db461d5adac8"
                }
            ],
            "startTime": 1682628698041724,
            "duration": 466,
            "tags": [
                {
                    "key": "internal.span.format",
                    "type": "string",
                    "value": "proto"
                }
            ],
            "logs": [],
            "processID": "p2",
            "warnings": null
        },
        {
            "traceID": "c1b550e8b0f4a312",
            "spanID": "bce8072d653508c7",
            "flags": 1,
            "operationName": "UploadMovieId",
            "references": [
                {
                    "refType": "CHILD_OF",
                    "traceID": "c1b550e8b0f4a312",
                    "spanID": "8b12023aeceaf54c"
                }
            ],
            "startTime": 1682628698041720,
            "duration": 329,
            "tags": [
                {
                    "key": "internal.span.format",
                    "type": "string",
                    "value": "proto"
                }
            ],
            "logs": [],
            "processID": "p2",
            "warnings": null
        },
        {
            "traceID": "c1b550e8b0f4a312",
            "spanID": "102deca7d6b64a2f",
            "flags": 1,
            "operationName": "UploadText",
            "references": [
                {
                    "refType": "CHILD_OF",
                    "traceID": "c1b550e8b0f4a312",
                    "spanID": "99d77ce6b6e4ec42"
                }
            ],
            "startTime": 1682628698041397,
            "duration": 438,
            "tags": [
                {
                    "key": "internal.span.format",
                    "type": "string",
                    "value": "proto"
                }
            ],
            "logs": [],
            "processID": "p2",
            "warnings": null
        },
        {
            "traceID": "c1b550e8b0f4a312",
            "spanID": "1084c5cec83c158c",
            "flags": 1,
            "operationName": "UploadRating",
            "references": [
                {
                    "refType": "CHILD_OF",
                    "traceID": "c1b550e8b0f4a312",
                    "spanID": "433b9ba255e5cce2"
                }
            ],
            "startTime": 1682628698041844,
            "duration": 2194,
            "tags": [
                {
                    "key": "internal.span.format",
                    "type": "string",
                    "value": "proto"
                }
            ],
            "logs": [],
            "processID": "p2",
            "warnings": null
        },
        {
            "traceID": "c1b550e8b0f4a312",
            "spanID": "c980c8a247a392fb",
            "flags": 1,
            "operationName": "UploadUserReview",
            "references": [
                {
                    "refType": "CHILD_OF",
                    "traceID": "c1b550e8b0f4a312",
                    "spanID": "1084c5cec83c158c"
                }
            ],
            "startTime": 1682628698042603,
            "duration": 1101,
            "tags": [
                {
                    "key": "internal.span.format",
                    "type": "string",
                    "value": "proto"
                }
            ],
            "logs": [],
            "processID": "p3",
            "warnings": null
        },
        {
            "traceID": "c1b550e8b0f4a312",
            "spanID": "4626162a2ad80c7f",
            "flags": 1,
            "operationName": "MongoFindUser",
            "references": [
                {
                    "refType": "CHILD_OF",
                    "traceID": "c1b550e8b0f4a312",
                    "spanID": "c980c8a247a392fb"
                }
            ],
            "startTime": 1682628698042641,
            "duration": 1065,
            "tags": [
                {
                    "key": "internal.span.format",
                    "type": "string",
                    "value": "proto"
                }
            ],
            "logs": [],
            "processID": "p3",
            "warnings": null
        },
        {
            "traceID": "c1b550e8b0f4a312",
            "spanID": "462072876a84591b",
            "flags": 1,
            "operationName": "MongoUpdate",
            "references": [
                {
                    "refType": "CHILD_OF",
                    "traceID": "c1b550e8b0f4a312",
                    "spanID": "c980c8a247a392fb"
                }
            ],
            "startTime": 1682628698043025,
            "duration": 434,
            "tags": [
                {
                    "key": "internal.span.format",
                    "type": "string",
                    "value": "proto"
                }
            ],
            "logs": [],
            "processID": "p3",
            "warnings": null
        },
        {
            "traceID": "c1b550e8b0f4a312",
            "spanID": "076713d94414ef14",
            "flags": 1,
            "operationName": "RedisUpdate",
            "references": [
                {
                    "refType": "CHILD_OF",
                    "traceID": "c1b550e8b0f4a312",
                    "spanID": "c980c8a247a392fb"
                }
            ],
            "startTime": 1682628698043480,
            "duration": 210,
            "tags": [
                {
                    "key": "internal.span.format",
                    "type": "string",
                    "value": "proto"
                }
            ],
            "logs": [],
            "processID": "p3",
            "warnings": null
        },
        {
            "traceID": "c1b550e8b0f4a312",
            "spanID": "06ac2c6ad3e8a69c",
            "flags": 1,
            "operationName": "UploadUniqueId",
            "references": [
                {
                    "refType": "CHILD_OF",
                    "traceID": "c1b550e8b0f4a312",
                    "spanID": "792007a846520d7d"
                }
            ],
            "startTime": 1682628698041376,
            "duration": 571,
            "tags": [
                {
                    "key": "internal.span.format",
                    "type": "string",
                    "value": "proto"
                }
            ],
            "logs": [],
            "processID": "p4",
            "warnings": null
        },
        {
            "traceID": "c1b550e8b0f4a312",
            "spanID": "bb4d3b9a9ea43af5",
            "flags": 1,
            "operationName": "MongoFindMovie",
            "references": [
                {
                    "refType": "CHILD_OF",
                    "traceID": "c1b550e8b0f4a312",
                    "spanID": "9869a45a44d6ccef"
                }
            ],
            "startTime": 1682628698042660,
            "duration": 1200,
            "tags": [
                {
                    "key": "internal.span.format",
                    "type": "string",
                    "value": "proto"
                }
            ],
            "logs": [],
            "processID": "p5",
            "warnings": null
        },
        {
            "traceID": "c1b550e8b0f4a312",
            "spanID": "39c1d4afd184c1fb",
            "flags": 1,
            "operationName": "MongoUpdate.",
            "references": [
                {
                    "refType": "CHILD_OF",
                    "traceID": "c1b550e8b0f4a312",
                    "spanID": "9869a45a44d6ccef"
                }
            ],
            "startTime": 1682628698043110,
            "duration": 456,
            "tags": [
                {
                    "key": "internal.span.format",
                    "type": "string",
                    "value": "proto"
                }
            ],
            "logs": [],
            "processID": "p5",
            "warnings": null
        },
        {
            "traceID": "c1b550e8b0f4a312",
            "spanID": "3d5b93afbc499493",
            "flags": 1,
            "operationName": "RedisUpdate",
            "references": [
                {
                    "refType": "CHILD_OF",
                    "traceID": "c1b550e8b0f4a312",
                    "spanID": "9869a45a44d6ccef"
                }
            ],
            "startTime": 1682628698043588,
            "duration": 256,
            "tags": [
                {
                    "key": "internal.span.format",
                    "type": "string",
                    "value": "proto"
                }
            ],
            "logs": [],
            "processID": "p5",
            "warnings": null
        },
        {
            "traceID": "c1b550e8b0f4a312",
            "spanID": "9869a45a44d6ccef",
            "flags": 1,
            "operationName": "UploadMovieReview",
            "references": [
                {
                    "refType": "CHILD_OF",
                    "traceID": "c1b550e8b0f4a312",
                    "spanID": "1084c5cec83c158c"
                }
            ],
            "startTime": 1682628698042634,
            "duration": 1220,
            "tags": [
                {
                    "key": "internal.span.format",
                    "type": "string",
                    "value": "proto"
                }
            ],
            "logs": [],
            "processID": "p5",
            "warnings": null
        },
        {
            "traceID": "c1b550e8b0f4a312",
            "spanID": "6da5b6434d26430a",
            "flags": 1,
            "operationName": "MmcGetUserId",
            "references": [
                {
                    "refType": "CHILD_OF",
                    "traceID": "c1b550e8b0f4a312",
                    "spanID": "dff5db461d5adac8"
                }
            ],
            "startTime": 1682628698041451,
            "duration": 108,
            "tags": [
                {
                    "key": "internal.span.format",
                    "type": "string",
                    "value": "proto"
                }
            ],
            "logs": [],
            "processID": "p6",
            "warnings": null
        },
        {
            "traceID": "c1b550e8b0f4a312",
            "spanID": "dff5db461d5adac8",
            "flags": 1,
            "operationName": "UploadUserWithUsername",
            "references": [
                {
                    "refType": "CHILD_OF",
                    "traceID": "c1b550e8b0f4a312",
                    "spanID": "792007a846520d7d"
                }
            ],
            "startTime": 1682628698041432,
            "duration": 817,
            "tags": [
                {
                    "key": "internal.span.format",
                    "type": "string",
                    "value": "proto"
                }
            ],
            "logs": [],
            "processID": "p6",
            "warnings": null
        },
        {
            "traceID": "c1b550e8b0f4a312",
            "spanID": "8bf8dc6ce21a71e5",
            "flags": 1,
            "operationName": "MmcSetMovieId",
            "references": [
                {
                    "refType": "CHILD_OF",
                    "traceID": "c1b550e8b0f4a312",
                    "spanID": "8b12023aeceaf54c"
                }
            ],
            "startTime": 1682628698041588,
            "duration": 91,
            "tags": [
                {
                    "key": "internal.span.format",
                    "type": "string",
                    "value": "proto"
                }
            ],
            "logs": [],
            "processID": "p7",
            "warnings": null
        },
        {
            "traceID": "c1b550e8b0f4a312",
            "spanID": "20079d71e9e84afe",
            "flags": 1,
            "operationName": "MmcGetMovieId",
            "references": [
                {
                    "refType": "CHILD_OF",
                    "traceID": "c1b550e8b0f4a312",
                    "spanID": "8b12023aeceaf54c"
                }
            ],
            "startTime": 1682628698041230,
            "duration": 122,
            "tags": [
                {
                    "key": "internal.span.format",
                    "type": "string",
                    "value": "proto"
                }
            ],
            "logs": [],
            "processID": "p7",
            "warnings": null
        },
        {
            "traceID": "c1b550e8b0f4a312",
            "spanID": "8b12023aeceaf54c",
            "flags": 1,
            "operationName": "UploadMovieId",
            "references": [
                {
                    "refType": "CHILD_OF",
                    "traceID": "c1b550e8b0f4a312",
                    "spanID": "792007a846520d7d"
                }
            ],
            "startTime": 1682628698041211,
            "duration": 3236,
            "tags": [
                {
                    "key": "internal.span.format",
                    "type": "string",
                    "value": "proto"
                }
            ],
            "logs": [],
            "processID": "p7",
            "warnings": null
        },
        {
            "traceID": "c1b550e8b0f4a312",
            "spanID": "18b9cbd4cd355a75",
            "flags": 1,
            "operationName": "RedisInsert",
            "references": [
                {
                    "refType": "CHILD_OF",
                    "traceID": "c1b550e8b0f4a312",
                    "spanID": "433b9ba255e5cce2"
                }
            ],
            "startTime": 1682628698041794,
            "duration": 276,
            "tags": [
                {
                    "key": "internal.span.format",
                    "type": "string",
                    "value": "proto"
                }
            ],
            "logs": [],
            "processID": "p8",
            "warnings": null
        },
        {
            "traceID": "c1b550e8b0f4a312",
            "spanID": "433b9ba255e5cce2",
            "flags": 1,
            "operationName": "UploadRating",
            "references": [
                {
                    "refType": "CHILD_OF",
                    "traceID": "c1b550e8b0f4a312",
                    "spanID": "8b12023aeceaf54c"
                }
            ],
            "startTime": 1682628698041685,
            "duration": 2625,
            "tags": [
                {
                    "key": "internal.span.format",
                    "type": "string",
                    "value": "proto"
                }
            ],
            "logs": [],
            "processID": "p8",
            "warnings": null
        },
        {
            "traceID": "c1b550e8b0f4a312",
            "spanID": "792007a846520d7d",
            "flags": 1,
            "operationName": "ComposeReview",
            "references": [
                {
                    "refType": "CHILD_OF",
                    "traceID": "c1b550e8b0f4a312",
                    "spanID": "9b27ee04777bb9eb"
                }
            ],
            "startTime": 1682628698040880,
            "duration": 3685,
            "tags": [
                {
                    "key": "internal.span.format",
                    "type": "string",
                    "value": "proto"
                }
            ],
            "logs": [],
            "processID": "p9",
            "warnings": null
        },
        {
            "traceID": "c1b550e8b0f4a312",
            "spanID": "9b27ee04777bb9eb",
            "flags": 1,
            "operationName": "/wrk2-api/review/compose",
            "references": [
                {
                    "refType": "CHILD_OF",
                    "traceID": "c1b550e8b0f4a312",
                    "spanID": "c1b550e8b0f4a312"
                }
            ],
            "startTime": 1682628698040832,
            "duration": 3794,
            "tags": [
                {
                    "key": "component",
                    "type": "string",
                    "value": "nginx"
                },
                {
                    "key": "nginx.worker_pid",
                    "type": "string",
                    "value": "10"
                },
                {
                    "key": "peer.address",
                    "type": "string",
                    "value": "172.18.0.1:40634"
                },
                {
                    "key": "http.method",
                    "type": "string",
                    "value": "POST"
                },
                {
                    "key": "http.url",
                    "type": "string",
                    "value": "http://localhost:8080/wrk2-api/review/compose/wrk2-api/review/compose"
                },
                {
                    "key": "http.host",
                    "type": "string",
                    "value": "localhost:8080"
                },
                {
                    "key": "http.status_code",
                    "type": "int64",
                    "value": 200
                },
                {
                    "key": "http.status_line",
                    "type": "string",
                    "value": ""
                },
                {
                    "key": "internal.span.format",
                    "type": "string",
                    "value": "proto"
                }
            ],
            "logs": [],
            "processID": "p9",
            "warnings": null
        },
        {
            "traceID": "c1b550e8b0f4a312",
            "spanID": "c1b550e8b0f4a312",
            "flags": 1,
            "operationName": "/wrk2-api/review/compose",
            "references": [],
            "startTime": 1682628698040000,
            "duration": 4627,
            "tags": [
                {
                    "key": "sampler.type",
                    "type": "string",
                    "value": "const"
                },
                {
                    "key": "sampler.param",
                    "type": "bool",
                    "value": true
                },
                {
                    "key": "http.status_code",
                    "type": "int64",
                    "value": 200
                },
                {
                    "key": "http.status_line",
                    "type": "string",
                    "value": ""
                },
                {
                    "key": "component",
                    "type": "string",
                    "value": "nginx"
                },
                {
                    "key": "nginx.worker_pid",
                    "type": "string",
                    "value": "10"
                },
                {
                    "key": "peer.address",
                    "type": "string",
                    "value": "172.18.0.1:40634"
                },
                {
                    "key": "http.method",
                    "type": "string",
                    "value": "POST"
                },
                {
                    "key": "http.url",
                    "type": "string",
                    "value": "http://localhost:8080/wrk2-api/review/compose/wrk2-api/review/compose"
                },
                {
                    "key": "http.host",
                    "type": "string",
                    "value": "localhost:8080"
                },
                {
                    "key": "internal.span.format",
                    "type": "string",
                    "value": "proto"
                }
            ],
            "logs": [],
            "processID": "p9",
            "warnings": null
        },
        {
            "traceID": "c1b550e8b0f4a312",
            "spanID": "3b4f6dcc57f14e48",
            "flags": 1,
            "operationName": "StoreReview",
            "references": [
                {
                    "refType": "CHILD_OF",
                    "traceID": "c1b550e8b0f4a312",
                    "spanID": "1084c5cec83c158c"
                }
            ],
            "startTime": 1682628698042583,
            "duration": 311,
            "tags": [
                {
                    "key": "internal.span.format",
                    "type": "string",
                    "value": "proto"
                }
            ],
            "logs": [],
            "processID": "p1",
            "warnings": null
        },
        {
            "traceID": "c1b550e8b0f4a312",
            "spanID": "99d77ce6b6e4ec42",
            "flags": 1,
            "operationName": "UploadText",
            "references": [
                {
                    "refType": "CHILD_OF",
                    "traceID": "c1b550e8b0f4a312",
                    "spanID": "792007a846520d7d"
                }
            ],
            "startTime": 1682628698041297,
            "duration": 596,
            "tags": [
                {
                    "key": "internal.span.format",
                    "type": "string",
                    "value": "proto"
                }
            ],
            "logs": [],
            "processID": "p10",
            "warnings": null
        }
    ],
    "processes": {
        "p1": {
            "serviceName": "review-storage-service",
            "tags": [
                {
                    "key": "hostname",
                    "type": "string",
                    "value": "review-storage-service"
                },
                {
                    "key": "ip",
                    "type": "string",
                    "value": "127.0.0.1"
                },
                {
                    "key": "jaeger.version",
                    "type": "string",
                    "value": "C++-0.4.2"
                }
            ]
        },
        "p10": {
            "serviceName": "text-service",
            "tags": [
                {
                    "key": "hostname",
                    "type": "string",
                    "value": "text-service"
                },
                {
                    "key": "ip",
                    "type": "string",
                    "value": "127.0.0.1"
                },
                {
                    "key": "jaeger.version",
                    "type": "string",
                    "value": "C++-0.4.2"
                }
            ]
        },
        "p2": {
            "serviceName": "compose-review-service",
            "tags": [
                {
                    "key": "hostname",
                    "type": "string",
                    "value": "compose-review-service"
                },
                {
                    "key": "ip",
                    "type": "string",
                    "value": "127.0.0.1"
                },
                {
                    "key": "jaeger.version",
                    "type": "string",
                    "value": "C++-0.4.2"
                }
            ]
        },
        "p3": {
            "serviceName": "user-review-service",
            "tags": [
                {
                    "key": "hostname",
                    "type": "string",
                    "value": "user-review-service"
                },
                {
                    "key": "ip",
                    "type": "string",
                    "value": "127.0.0.1"
                },
                {
                    "key": "jaeger.version",
                    "type": "string",
                    "value": "C++-0.4.2"
                }
            ]
        },
        "p4": {
            "serviceName": "unique-id-service",
            "tags": [
                {
                    "key": "hostname",
                    "type": "string",
                    "value": "unique-id-service"
                },
                {
                    "key": "ip",
                    "type": "string",
                    "value": "127.0.0.1"
                },
                {
                    "key": "jaeger.version",
                    "type": "string",
                    "value": "C++-0.4.2"
                }
            ]
        },
        "p5": {
            "serviceName": "movie-review-service",
            "tags": [
                {
                    "key": "hostname",
                    "type": "string",
                    "value": "movie-review-service"
                },
                {
                    "key": "ip",
                    "type": "string",
                    "value": "127.0.0.1"
                },
                {
                    "key": "jaeger.version",
                    "type": "string",
                    "value": "C++-0.4.2"
                }
            ]
        },
        "p6": {
            "serviceName": "user-service",
            "tags": [
                {
                    "key": "hostname",
                    "type": "string",
                    "value": "user-service"
                },
                {
                    "key": "ip",
                    "type": "string",
                    "value": "127.0.0.1"
                },
                {
                    "key": "jaeger.version",
                    "type": "string",
                    "value": "C++-0.4.2"
                }
            ]
        },
        "p7": {
            "serviceName": "movie-id-service",
            "tags": [
                {
                    "key": "hostname",
                    "type": "string",
                    "value": "movie-id-service"
                },
                {
                    "key": "ip",
                    "type": "string",
                    "value": "127.0.0.1"
                },
                {
                    "key": "jaeger.version",
                    "type": "string",
                    "value": "C++-0.4.2"
                }
            ]
        },
        "p8": {
            "serviceName": "rating-service",
            "tags": [
                {
                    "key": "hostname",
                    "type": "string",
                    "value": "rating-service"
                },
                {
                    "key": "ip",
                    "type": "string",
                    "value": "127.0.0.1"
                },
                {
                    "key": "jaeger.version",
                    "type": "string",
                    "value": "C++-0.4.2"
                }
            ]
        },
        "p9": {
            "serviceName": "nginx",
            "tags": [
                {
                    "key": "hostname",
                    "type": "string",
                    "value": "nginx-thrift"
                },
                {
                    "key": "ip",
                    "type": "string",
                    "value": "127.0.0.1"
                },
                {
                    "key": "jaeger.version",
                    "type": "string",
                    "value": "C++-0.4.2"
                }
            ]
        }
    },
    "warnings": null
}